{
  "game_info": {
    "game_id": "401776264",
    "teams": [
      {
        "abbreviation": "DET",
        "name": "Detroit Lions",
        "score": 17,
        "home_away": "home"
      },
      {
        "abbreviation": "MIA",
        "name": "Miami Dolphins",
        "score": 24,
        "home_away": "away"
      }
    ],
    "final_score": {}
  },
  "drives": [
    {
      "id": "4017762641",
      "team": "DET",
      "plays_count": 9,
      "result": "PUNT",
      "yards": 0
    },
    {
      "id": "4017762642",
      "team": "MIA",
      "plays_count": 6,
      "result": "PUNT",
      "yards": 2
    },
    {
      "id": "4017762643",
      "team": "DET",
      "plays_count": 6,
      "result": "PUNT",
      "yards": -12
    },
    {
      "id": "4017762644",
      "team": "MIA",
      "plays_count": 14,
      "result": "TD",
      "yards": 80
    },
    {
      "id": "4017762645",
      "team": "DET",
      "plays_count": 9,
      "result": "PUNT",
      "yards": 16
    },
    {
      "id": "4017762646",
      "team": "MIA",
      "plays_count": 7,
      "result": "PUNT",
      "yards": 0
    },
    {
      "id": "4017762647",
      "team": "DET",
      "plays_count": 12,
      "result": "TD",
      "yards": 63
    },
    {
      "id": "4017762648",
      "team": "MIA",
      "plays_count": 16,
      "result": "DOWNS",
      "yards": 56
    },
    {
      "id": "4017762649",
      "team": "DET",
      "plays_count": 13,
      "result": "TD",
      "yards": 83
    },
    {
      "id": "40177626410",
      "team": "MIA",
      "plays_count": 4,
      "result": "END OF HALF",
      "yards": 20
    },
    {
      "id": "40177626411",
      "team": "MIA",
      "plays_count": 5,
      "result": "PUNT",
      "yards": 4
    },
    {
      "id": "40177626412",
      "team": "DET",
      "plays_count": 5,
      "result": "PUNT",
      "yards": -7
    },
    {
      "id": "40177626413",
      "team": "MIA",
      "plays_count": 5,
      "result": "TD",
      "yards": 36
    },
    {
      "id": "40177626414",
      "team": "DET",
      "plays_count": 5,
      "result": "PUNT",
      "yards": -1
    },
    {
      "id": "40177626415",
      "team": "DET",
      "plays_count": 10,
      "result": "FG",
      "yards": 12
    },
    {
      "id": "40177626416",
      "team": "MIA",
      "plays_count": 6,
      "result": "PUNT",
      "yards": -3
    },
    {
      "id": "40177626417",
      "team": "DET",
      "plays_count": 6,
      "result": "PUNT",
      "yards": 6
    },
    {
      "id": "40177626418",
      "team": "MIA",
      "plays_count": 9,
      "result": "TD",
      "yards": 60
    },
    {
      "id": "40177626419",
      "team": "DET",
      "plays_count": 9,
      "result": "PUNT",
      "yards": 15
    },
    {
      "id": "40177626420",
      "team": "MIA",
      "plays_count": 20,
      "result": "FG",
      "yards": 92
    },
    {
      "id": "40177626421",
      "team": "DET",
      "plays_count": 12,
      "result": "INT",
      "yards": 48
    },
    {
      "id": "40177626422",
      "team": "MIA",
      "plays_count": 2,
      "result": "END OF GAME",
      "yards": -1
    }
  ],
  "plays": [
    {
      "id": "40177626439",
      "text": "J.Sanders kicks 59 yards from MIA 35 to DET 6. G.Stuard to DET 29 for 23 yards (C.Goode).",
      "type": "Kickoff",
      "down": 0,
      "distance": 0,
      "yard_line": 65,
      "period": 1,
      "clock": "15:00",
      "team": "",
      "scoring_play": false
    },
    {
      "id": "40177626462",
      "text": "(Shotgun) K.Allen pass short left to J.Meeks pushed ob at DET 40 for 11 yards (C.Armstrong).",
      "type": "Pass Reception",
      "down": 1,
      "distance": 10,
      "yard_line": 29,
      "period": 1,
      "clock": "14:55",
      "team": "",
      "scoring_play": false
    },
    {
      "id": "40177626492",
      "text": "K.Allen pass short left to T.Kennedy pushed ob at DET 48 for 8 yards (W.Gay).",
      "type": "Pass Reception",
      "down": 1,
      "distance": 10,
      "yard_line": 40,
      "period": 1,
      "clock": "14:27",
      "team": "",
      "scoring_play": false
    },
    {
      "id": "401776264122",
      "text": "C.Reynolds right tackle to DET 49 for 1 yard (D.Trader; K.Grant).",
      "type": "Rush",
      "down": 2,
      "distance": 2,
      "yard_line": 48,
      "period": 1,
      "clock": "13:54",
      "team": "",
      "scoring_play": false
    },
    {
      "id": "401776264144",
      "text": "C.Reynolds left end pushed ob at MIA 19 for 32 yards (I.Melifonwu; E.Bonner).PENALTY on DET-T.Kennedy, Offensive Holding, 10 yards, enforced at 50.",
      "type": "Rush",
      "down": 3,
      "distance": 1,
      "yard_line": 49,
      "period": 1,
      "clock": "13:18",
      "team": "",
      "scoring_play": false
    },
    {
      "id": "401776264182",
      "text": "(Shotgun) PENALTY on DET, Delay of Game, 5 yards, enforced at DET 40 - No Play.",
      "type": "Penalty",
      "down": 3,
      "distance": 10,
      "yard_line": 40,
      "period": 1,
      "clock": "12:42",
      "team": "",
      "scoring_play": false
    },
    {
      "id": "401776264206",
      "text": "(Shotgun) K.Allen pass short left to S.Vaki to DET 29 for -6 yards (W.Gay).",
      "type": "Pass Reception",
      "down": 3,
      "distance": 15,
      "yard_line": 35,
      "period": 1,
      "clock": "12:24",
      "team": "",
      "scoring_play": false
    },
    {
      "id": "401776264231",
      "text": "J.Fox punts 45 yards to MIA 26, Center-H.Hatten. D.Eskridge to MIA 34 for 8 yards (S.Vaki). FUMBLES (S.Vaki), recovered by MIA-C.Tindall at MIA 29.",
      "type": "Fumble Recovery (Own)",
      "down": 4,
      "distance": 21,
      "yard_line": 29,
      "period": 1,
      "clock": "11:43",
      "team": "",
      "scoring_play": false
    },
    {
      "id": "401776264252",
      "text": "Official Timeout at 11:28.",
      "type": "Official Timeout",
      "down": 1,
      "distance": 10,
      "yard_line": 71,
      "period": 1,
      "clock": "11:28",
      "team": "",
      "scoring_play": false
    },
    {
      "id": "401776264273",
      "text": "(Shotgun) Z.Wilson pass short left to E.Ezukanma to MIA 32 for 3 yards (C.Smith).",
      "type": "Pass Reception",
      "down": 1,
      "distance": 10,
      "yard_line": 71,
      "period": 1,
      "clock": "11:28",
      "team": "",
      "scoring_play": false
    },
    {
      "id": "401776264305",
      "text": "(Shotgun) PENALTY on MIA-P.Brown, False Start, 5 yards, enforced at MIA 32 - No Play.",
      "type": "Penalty",
      "down": 2,
      "distance": 7,
      "yard_line": 68,
      "period": 1,
      "clock": "10:50",
      "team": "",
      "scoring_play": false
    },
    {
      "id": "401776264329",
      "text": "(Shotgun) Z.Wilson pass short left to T.Conner pushed ob at MIA 31 for 4 yards (G.Stuard).",
      "type": "Pass Reception",
      "down": 2,
      "distance": 12,
      "yard_line": 73,
      "period": 1,
      "clock": "10:31",
      "team": "",
      "scoring_play": false
    },
    {
      "id": "401776264359",
      "text": "(Shotgun) Z.Wilson pass incomplete short middle to D.Eskridge (Z.Cunningham) [Z.Cunningham].",
      "type": "Pass Incompletion",
      "down": 3,
      "distance": 8,
      "yard_line": 69,
      "period": 1,
      "clock": "9:51",
      "team": "",
      "scoring_play": false
    },
    {
      "id": "401776264382",
      "text": "R.Stonehouse punts 38 yards to DET 31, Center-J.Cardona, downed by MIA-J.Cardona.",
      "type": "Punt",
      "down": 4,
      "distance": 8,
      "yard_line": 69,
      "period": 1,
      "clock": "9:46",
      "team": "",
      "scoring_play": false
    },
    {
      "id": "401776264392",
      "text": "Official Timeout at 09:38.",
      "type": "Official Timeout",
      "down": 1,
      "distance": 10,
      "yard_line": 31,
      "period": 1,
      "clock": "9:38",
      "team": "",
      "scoring_play": false
    },
    {
      "id": "401776264402",
      "text": "C.Reynolds left end pushed ob at DET 39 for 8 yards (K.Sheffield).PENALTY on DET-Z.Horton, Offensive Holding, 10 yards, enforced at DET 31 - No Play.",
      "type": "Penalty",
      "down": 1,
      "distance": 10,
      "yard_line": 31,
      "period": 1,
      "clock": "9:38",
      "team": "",
      "scoring_play": false
    },
    {
      "id": "401776264447",
      "text": "(Shotgun) K.Allen pass incomplete deep right to I.TeSlaa.",
      "type": "Pass Incompletion",
      "down": 1,
      "distance": 20,
      "yard_line": 21,
      "period": 1,
      "clock": "9:12",
      "team": "",
      "scoring_play": false
    },
    {
      "id": "401776264470",
      "text": "S.Vaki left tackle to DET 23 for 2 yards (K.Britt).",
      "type": "Rush",
      "down": 2,
      "distance": 20,
      "yard_line": 21,
      "period": 1,
      "clock": "9:07",
      "team": "",
      "scoring_play": false
    },
    {
      "id": "401776264492",
      "text": "(Shotgun) K.Allen scrambles right end to DET 24 for 1 yard. K.Allen pass deep right to I.TeSlaa ran ob at DET 43 for 19 yards.PENALTY on DET-K.Allen, Illegal Forward Pass, 5 yards, enforced at DET 24.",
      "type": "Pass Reception",
      "down": 3,
      "distance": 18,
      "yard_line": 23,
      "period": 1,
      "clock": "8:27",
      "team": "",
      "scoring_play": false
    },
    {
      "id": "401776264533",
      "text": "J.Fox punts 63 yards to MIA 18, Center-H.Hatten. D.Eskridge ran ob at MIA 46 for 28 yards (H.Hatten).PENALTY on MIA-J.Marshall, Illegal Block Above the Waist, 10 yards, enforced at MIA 30.",
      "type": "Punt",
      "down": 4,
      "distance": 22,
      "yard_line": 19,
      "period": 1,
      "clock": "8:15",
      "team": "",
      "scoring_play": false
    },
    {
      "id": "401776264565",
      "text": "Official Timeout at 07:59.",
      "type": "Official Timeout",
      "down": 1,
      "distance": 10,
      "yard_line": 80,
      "period": 1,
      "clock": "7:59",
      "team": "",
      "scoring_play": false
    },
    {
      "id": "401776264597",
      "text": "(Shotgun) J.Wright left tackle to MIA 20 for no gain (K.Cooper; C.Smith).",
      "type": "Rush",
      "down": 1,
      "distance": 10,
      "yard_line": 80,
      "period": 1,
      "clock": "7:59",
      "team": "",
      "scoring_play": false
    },
    {
      "id": "401776264627",
      "text": "(Shotgun) Z.Wilson pass short left to T.Conner to MIA 33 for 13 yards (G.Stuard, I.Kennelly).",
      "type": "Pass Reception",
      "down": 2,
      "distance": 10,
      "yard_line": 80,
      "period": 1,
      "clock": "7:15",
      "team": "",
      "scoring_play": false
    },
    {
      "id": "401776264652",
      "text": "(Shotgun) Z.Wilson pass incomplete short right to E.Ezukanma.",
      "type": "Pass Incompletion",
      "down": 1,
      "distance": 10,
      "yard_line": 67,
      "period": 1,
      "clock": "6:36",
      "team": "",
      "scoring_play": false
    },
    {
      "id": "401776264675",
      "text": "(Shotgun) Z.Wilson pass short middle to T.Washington pushed ob at MIA 42 for 9 yards (A.Maddox).",
      "type": "Pass Reception",
      "down": 2,
      "distance": 10,
      "yard_line": 67,
      "period": 1,
      "clock": "6:32",
      "team": "",
      "scoring_play": false
    },
    {
      "id": "401776264716",
      "text": "(Shotgun) J.Wright up the middle to MIA 43 for 1 yard (A.Muhammad; Z.Cunningham).",
      "type": "Rush",
      "down": 3,
      "distance": 1,
      "yard_line": 58,
      "period": 1,
      "clock": "5:49",
      "team": "",
      "scoring_play": false
    },
    {
      "id": "401776264738",
      "text": "Z.Wilson pass short right to T.Conner pushed ob at 50 for 7 yards (T.Russell, Z.Cunningham).",
      "type": "Pass Reception",
      "down": 1,
      "distance": 10,
      "yard_line": 57,
      "period": 1,
      "clock": "5:23",
      "team": "",
      "scoring_play": false
    },
    {
      "id": "401776264763",
      "text": "Z.Wilson pass short right to D.Eskridge ran ob at DET 35 for 15 yards (T.Russell).",
      "type": "Pass Reception",
      "down": 2,
      "distance": 3,
      "yard_line": 50,
      "period": 1,
      "clock": "4:46",
      "team": "",
      "scoring_play": false
    },
    {
      "id": "401776264798",
      "text": "J.Wright left tackle to DET 32 for 3 yards (C.Smith).",
      "type": "Rush",
      "down": 1,
      "distance": 10,
      "yard_line": 35,
      "period": 1,
      "clock": "4:08",
      "team": "",
      "scoring_play": false
    },
    {
      "id": "401776264820",
      "text": "(Shotgun) Z.Wilson pass short left to P.Brown to DET 2 for 30 yards (I.Kennelly; G.Stuard) [P.O'Connor].PENALTY on MIA-L.Borom, Illegal Formation, 5 yards, enforced at DET 32 - No Play.",
      "type": "Penalty",
      "down": 2,
      "distance": 7,
      "yard_line": 32,
      "period": 1,
      "clock": "3:27",
      "team": "",
      "scoring_play": false
    },
    {
      "id": "401776264856",
      "text": "(Shotgun) Z.Wilson pass incomplete deep left to E.Ezukanma (D.Miller).",
      "type": "Pass Incompletion",
      "down": 2,
      "distance": 12,
      "yard_line": 37,
      "period": 1,
      "clock": "3:05",
      "team": "",
      "scoring_play": false
    },
    {
      "id": "401776264868",
      "text": "Timeout #1 by MIA at 02:59.",
      "type": "Timeout",
      "down": 3,
      "distance": 12,
      "yard_line": 37,
      "period": 1,
      "clock": "2:59",
      "team": "",
      "scoring_play": false
    },
    {
      "id": "401776264879",
      "text": "(Shotgun) Z.Wilson pass short right to D.Eskridge to DET 10 for 27 yards (A.Muhammad).",
      "type": "Pass Reception",
      "down": 3,
      "distance": 12,
      "yard_line": 37,
      "period": 1,
      "clock": "2:59",
      "team": "",
      "scoring_play": false
    },
    {
      "id": "401776264911",
      "text": "J.Wright left end to DET 9 for 1 yard (G.Stuard). FUMBLES (G.Stuard), recovered by MIA-T.Conner at DET 11. T.Conner to DET 11 for no gain (D.Miller, I.Kennelly).",
      "type": "Fumble Recovery (Own)",
      "down": 1,
      "distance": 10,
      "yard_line": 10,
      "period": 1,
      "clock": "2:18",
      "team": "",
      "scoring_play": false
    },
    {
      "id": "401776264949",
      "text": "(Shotgun) Z.Wilson pass short left to D.Eskridge for 11 yards, TOUCHDOWN. J.Sanders extra point is GOOD, Center-J.Cardona, Holder-J.Bailey.",
      "type": "Passing Touchdown",
      "down": 2,
      "distance": 11,
      "yard_line": 11,
      "period": 1,
      "clock": "1:24",
      "team": "",
      "scoring_play": true
    },
    {
      "id": "401776264990",
      "text": "J.Sanders kicks 62 yards from MIA 35 to DET 3. G.Stuard to DET 30 for 27 yards (Q.Bell).",
      "type": "Kickoff",
      "down": 0,
      "distance": 0,
      "yard_line": 65,
      "period": 1,
      "clock": "1:24",
      "team": "",
      "scoring_play": false
    },
    {
      "id": "4017762641018",
      "text": "K.Allen pass incomplete short right to T.Kennedy.",
      "type": "Pass Incompletion",
      "down": 1,
      "distance": 10,
      "yard_line": 30,
      "period": 1,
      "clock": "1:19",
      "team": "",
      "scoring_play": false
    },
    {
      "id": "4017762641041",
      "text": "S.Vaki right tackle to DET 35 for 5 yards (Q.Bell; K.Grant).",
      "type": "Rush",
      "down": 2,
      "distance": 10,
      "yard_line": 30,
      "period": 1,
      "clock": "1:14",
      "team": "",
      "scoring_play": false
    },
    {
      "id": "4017762641063",
      "text": "(Shotgun) K.Allen pass short right to D.Lovett to DET 40 for 5 yards (W.Gay).",
      "type": "Pass Reception",
      "down": 3,
      "distance": 5,
      "yard_line": 35,
      "period": 1,
      "clock": "0:33",
      "team": "",
      "scoring_play": false
    },
    {
      "id": "4017762641088",
      "text": "END QUARTER 1",
      "type": "End Period",
      "down": 1,
      "distance": 10,
      "yard_line": 40,
      "period": 1,
      "clock": "0:00",
      "team": "",
      "scoring_play": false
    },
    {
      "id": "4017762641108",
      "text": "S.Vaki left tackle to DET 42 for 2 yards (D.Jackson; C.Goode).",
      "type": "Rush",
      "down": 1,
      "distance": 10,
      "yard_line": 40,
      "period": 2,
      "clock": "15:00",
      "team": "",
      "scoring_play": false
    },
    {
      "id": "4017762641135",
      "text": "(Shotgun) K.Allen pass short left to I.TeSlaa to DET 46 for 4 yards (K.Sheffield) [G.Murphy].",
      "type": "Pass Reception",
      "down": 2,
      "distance": 8,
      "yard_line": 42,
      "period": 2,
      "clock": "14:26",
      "team": "",
      "scoring_play": false
    },
    {
      "id": "4017762641160",
      "text": "(Shotgun) K.Allen pass incomplete short middle to D.Lovett.",
      "type": "Pass Incompletion",
      "down": 3,
      "distance": 4,
      "yard_line": 46,
      "period": 2,
      "clock": "13:50",
      "team": "",
      "scoring_play": false
    },
    {
      "id": "4017762641183",
      "text": "J.Fox punts 41 yards to MIA 13, Center-H.Hatten, fair catch by A.Henning.",
      "type": "Punt",
      "down": 4,
      "distance": 4,
      "yard_line": 46,
      "period": 2,
      "clock": "13:46",
      "team": "",
      "scoring_play": false
    },
    {
      "id": "4017762641203",
      "text": "(Shotgun) J.Wright right tackle to MIA 15 for 2 yards (A.Maddox).PENALTY on MIA-L.Borom, Illegal Formation, 5 yards, enforced at MIA 13 - No Play.",
      "type": "Penalty",
      "down": 1,
      "distance": 10,
      "yard_line": 87,
      "period": 2,
      "clock": "13:40",
      "team": "",
      "scoring_play": false
    },
    {
      "id": "4017762641236",
      "text": "(Shotgun) Z.Wilson pass incomplete short middle to J.Wright (G.Stuard).PENALTY on DET-A.Muhammad, Illegal Use of Hands, 5 yards, enforced at MIA 8 - No Play.",
      "type": "Penalty",
      "down": 1,
      "distance": 15,
      "yard_line": 92,
      "period": 2,
      "clock": "13:29",
      "team": "",
      "scoring_play": false
    },
    {
      "id": "4017762641270",
      "text": "(Shotgun) Z.Wilson pass incomplete deep right to T.Conner.",
      "type": "Pass Incompletion",
      "down": 1,
      "distance": 10,
      "yard_line": 87,
      "period": 2,
      "clock": "13:24",
      "team": "",
      "scoring_play": false
    },
    {
      "id": "4017762641293",
      "text": "Z.Wilson pass incomplete short left to D.Eskridge (A.George).",
      "type": "Pass Incompletion",
      "down": 2,
      "distance": 10,
      "yard_line": 87,
      "period": 2,
      "clock": "13:20",
      "team": "",
      "scoring_play": false
    },
    {
      "id": "4017762641316",
      "text": "(Shotgun) Z.Wilson pass incomplete deep right to T.Washington (L.Barcoo).",
      "type": "Pass Incompletion",
      "down": 3,
      "distance": 10,
      "yard_line": 87,
      "period": 2,
      "clock": "13:14",
      "team": "",
      "scoring_play": false
    },
    {
      "id": "4017762641339",
      "text": " J.Bailey punts 50 yards to DET 37, Center-J.Cardona, fair catch by D.Lovett.",
      "type": "Punt",
      "down": 4,
      "distance": 10,
      "yard_line": 87,
      "period": 2,
      "clock": "13:08",
      "team": "",
      "scoring_play": false
    },
    {
      "id": "4017762641349",
      "text": "Official Timeout at 13:00.",
      "type": "Official Timeout",
      "down": 1,
      "distance": 10,
      "yard_line": 37,
      "period": 2,
      "clock": "13:00",
      "team": "",
      "scoring_play": false
    },
    {
      "id": "4017762641359",
      "text": "C.Reynolds right end pushed ob at DET 44 for 7 yards (C.Goode).",
      "type": "Rush",
      "down": 1,
      "distance": 10,
      "yard_line": 37,
      "period": 2,
      "clock": "13:00",
      "team": "",
      "scoring_play": false
    },
    {
      "id": "4017762641393",
      "text": "(Shotgun) K.Allen sacked at DET 44 for 0 yards (C.Tindall).PENALTY on MIA-P.McMorris, Illegal Contact, 5 yards, enforced at DET 44 - No Play.",
      "type": "Penalty",
      "down": 2,
      "distance": 3,
      "yard_line": 44,
      "period": 2,
      "clock": "12:23",
      "team": "",
      "scoring_play": false
    },
    {
      "id": "4017762641426",
      "text": "C.Reynolds left tackle to MIA 47 for 4 yards (C.Goode).",
      "type": "Rush",
      "down": 1,
      "distance": 10,
      "yard_line": 49,
      "period": 2,
      "clock": "12:00",
      "team": "",
      "scoring_play": false
    },
    {
      "id": "4017762641448",
      "text": "(Shotgun) K.Allen pass short right to J.Meeks to MIA 39 for 8 yards (J.Jones; E.Asante).",
      "type": "Pass Reception",
      "down": 2,
      "distance": 6,
      "yard_line": 53,
      "period": 2,
      "clock": "11:24",
      "team": "",
      "scoring_play": false
    },
    {
      "id": "4017762641473",
      "text": "C.Reynolds right tackle to MIA 38 for 1 yard (Jo.Phillips).",
      "type": "Rush",
      "down": 1,
      "distance": 10,
      "yard_line": 61,
      "period": 2,
      "clock": "10:50",
      "team": "",
      "scoring_play": false
    },
    {
      "id": "4017762641495",
      "text": "(Shotgun) K.Allen pass short middle to I.TeSlaa to MIA 25 for 13 yards (P.McMorris).",
      "type": "Pass Reception",
      "down": 2,
      "distance": 9,
      "yard_line": 62,
      "period": 2,
      "clock": "10:12",
      "team": "",
      "scoring_play": false
    },
    {
      "id": "4017762641528",
      "text": "J.Saylors up the middle to MIA 14 for 11 yards (J.Colbert).",
      "type": "Rush",
      "down": 1,
      "distance": 10,
      "yard_line": 75,
      "period": 2,
      "clock": "9:39",
      "team": "",
      "scoring_play": false
    },
    {
      "id": "4017762641550",
      "text": "(Shotgun) J.Saylors left tackle to MIA 10 for 4 yards (Z.Biggers; E.Asante).",
      "type": "Rush",
      "down": 1,
      "distance": 10,
      "yard_line": 86,
      "period": 2,
      "clock": "9:03",
      "team": "",
      "scoring_play": false
    },
    {
      "id": "4017762641572",
      "text": "J.Saylors left tackle to MIA 10 for no gain (J.Marshall; Q.Bell).",
      "type": "Rush",
      "down": 2,
      "distance": 6,
      "yard_line": 90,
      "period": 2,
      "clock": "8:29",
      "team": "",
      "scoring_play": false
    },
    {
      "id": "4017762641594",
      "text": "C.Reynolds left end to MIA 11 for -1 yards (J.Colbert).",
      "type": "Rush",
      "down": 3,
      "distance": 6,
      "yard_line": 90,
      "period": 2,
      "clock": "7:48",
      "team": "",
      "scoring_play": false
    },
    {
      "id": "4017762641616",
      "text": "(Shotgun) K.Allen pass short left to J.Meeks for 11 yards, TOUCHDOWN. J.Bates extra point is GOOD, Center-H.Hatten, Holder-J.Fox.",
      "type": "Passing Touchdown",
      "down": 4,
      "distance": 7,
      "yard_line": 89,
      "period": 2,
      "clock": "7:00",
      "team": "",
      "scoring_play": true
    },
    {
      "id": "4017762641650",
      "text": "Official Timeout at 07:00.",
      "type": "Official Timeout",
      "down": 1,
      "distance": 10,
      "yard_line": 35,
      "period": 2,
      "clock": "7:00",
      "team": "",
      "scoring_play": false
    },
    {
      "id": "4017762641657",
      "text": "J.Bates kicks 65 yards from DET 35 to MIA 0. D.Eskridge to MIA 27 for 27 yards (A.Maddox; N.Lynn).",
      "type": "Kickoff",
      "down": 0,
      "distance": 0,
      "yard_line": 35,
      "period": 2,
      "clock": "7:00",
      "team": "",
      "scoring_play": false
    },
    {
      "id": "4017762641698",
      "text": "(Shotgun) Z.Wilson pass short middle to T.Washington to MIA 36 for 9 yards (E.Hallett; A.Maddox).",
      "type": "Pass Reception",
      "down": 1,
      "distance": 10,
      "yard_line": 73,
      "period": 2,
      "clock": "6:54",
      "team": "",
      "scoring_play": false
    },
    {
      "id": "4017762641723",
      "text": "(Shotgun) O.Gordon left tackle to MIA 36 for no gain (B.Martin; T.Nowaske).PENALTY on DET-B.Martin, Defensive Offside, 5 yards, enforced at MIA 36 - No Play.",
      "type": "Penalty",
      "down": 2,
      "distance": 1,
      "yard_line": 64,
      "period": 2,
      "clock": "6:14",
      "team": "",
      "scoring_play": false
    },
    {
      "id": "4017762641756",
      "text": "Z.Wilson pass incomplete deep right to D.Eskridge (E.Hallett).",
      "type": "Pass Incompletion",
      "down": 1,
      "distance": 10,
      "yard_line": 59,
      "period": 2,
      "clock": "5:51",
      "team": "",
      "scoring_play": false
    },
    {
      "id": "4017762641779",
      "text": "(Shotgun) Z.Wilson pass short right to T.Conner pushed ob at MIA 48 for 7 yards (G.Stuard).",
      "type": "Pass Reception",
      "down": 2,
      "distance": 10,
      "yard_line": 59,
      "period": 2,
      "clock": "5:43",
      "team": "",
      "scoring_play": false
    },
    {
      "id": "4017762641809",
      "text": "(Shotgun) Z.Wilson sacked at MIA 43 for -5 yards (I.Ukwu).PENALTY on DET-G.Stuard, Face Mask, 15 yards, enforced at MIA 48 - No Play.",
      "type": "Penalty",
      "down": 3,
      "distance": 3,
      "yard_line": 52,
      "period": 2,
      "clock": "5:06",
      "team": "",
      "scoring_play": false
    },
    {
      "id": "4017762641840",
      "text": "(Shotgun) Z.Wilson pass short left to T.Washington to DET 31 for 6 yards (N.Whiteside).",
      "type": "Pass Reception",
      "down": 1,
      "distance": 10,
      "yard_line": 37,
      "period": 2,
      "clock": "4:44",
      "team": "",
      "scoring_play": false
    },
    {
      "id": "4017762641865",
      "text": "O.Gordon left tackle to DET 29 for 2 yards (A.Maddox).",
      "type": "Rush",
      "down": 2,
      "distance": 4,
      "yard_line": 31,
      "period": 2,
      "clock": "4:10",
      "team": "",
      "scoring_play": false
    },
    {
      "id": "4017762641887",
      "text": "Z.Wilson pass short right to O.Gordon pushed ob at DET 15 for 14 yards (A.Pittman).",
      "type": "Pass Reception",
      "down": 3,
      "distance": 2,
      "yard_line": 29,
      "period": 2,
      "clock": "3:31",
      "team": "",
      "scoring_play": false
    },
    {
      "id": "4017762641917",
      "text": "(Shotgun) Z.Wilson pass short right to T.Conner ran ob at DET 9 for 6 yards.",
      "type": "Pass Reception",
      "down": 1,
      "distance": 10,
      "yard_line": 15,
      "period": 2,
      "clock": "2:53",
      "team": "",
      "scoring_play": false
    },
    {
      "id": "4017762641947",
      "text": "O.Gordon right end to DET 9 for no gain (M.Adams).",
      "type": "Rush",
      "down": 2,
      "distance": 4,
      "yard_line": 9,
      "period": 2,
      "clock": "2:29",
      "team": "",
      "scoring_play": false
    },
    {
      "id": "4017762641958",
      "text": "Two-Minute Warning",
      "type": "Two-minute warning",
      "down": 3,
      "distance": 4,
      "yard_line": 9,
      "period": 2,
      "clock": "2:00",
      "team": "",
      "scoring_play": false
    },
    {
      "id": "4017762641969",
      "text": "(Shotgun) Z.Wilson pass incomplete short right to T.Black.",
      "type": "Pass Incompletion",
      "down": 3,
      "distance": 4,
      "yard_line": 9,
      "period": 2,
      "clock": "2:00",
      "team": "",
      "scoring_play": false
    },
    {
      "id": "4017762641984",
      "text": "Timeout #2 by MIA at 01:55.",
      "type": "Timeout",
      "down": 4,
      "distance": 4,
      "yard_line": 9,
      "period": 2,
      "clock": "1:55",
      "team": "",
      "scoring_play": false
    },
    {
      "id": "4017762641999",
      "text": "(Shotgun) Z.Wilson sacked at DET 17 for -8 yards (I.Ukwu).",
      "type": "Sack",
      "down": 4,
      "distance": 4,
      "yard_line": 9,
      "period": 2,
      "clock": "1:55",
      "team": "",
      "scoring_play": false
    },
    {
      "id": "4017762642013",
      "text": "Official Timeout at 01:50.",
      "type": "Official Timeout",
      "down": 1,
      "distance": 10,
      "yard_line": 17,
      "period": 2,
      "clock": "1:50",
      "team": "",
      "scoring_play": false
    },
    {
      "id": "4017762642026",
      "text": "(Shotgun) S.Vaki up the middle to DET 31 for 14 yards (J.Saunders).",
      "type": "Rush",
      "down": 1,
      "distance": 10,
      "yard_line": 17,
      "period": 2,
      "clock": "1:50",
      "team": "",
      "scoring_play": false
    },
    {
      "id": "4017762642055",
      "text": "(No Huddle, Shotgun) K.Allen pass short left to Z.Horton ran ob at DET 37 for 6 yards (C.Tindall).",
      "type": "Pass Reception",
      "down": 1,
      "distance": 10,
      "yard_line": 31,
      "period": 2,
      "clock": "1:31",
      "team": "",
      "scoring_play": false
    },
    {
      "id": "4017762642085",
      "text": "(Shotgun) K.Allen sacked at DET 29 for -8 yards (G.Murphy).",
      "type": "Sack",
      "down": 2,
      "distance": 4,
      "yard_line": 37,
      "period": 2,
      "clock": "1:27",
      "team": "",
      "scoring_play": false
    },
    {
      "id": "4017762642095",
      "text": "Timeout #3 by MIA at 01:18.",
      "type": "Timeout",
      "down": 3,
      "distance": 12,
      "yard_line": 29,
      "period": 2,
      "clock": "1:18",
      "team": "",
      "scoring_play": false
    },
    {
      "id": "4017762642105",
      "text": "(Shotgun) K.Allen pass short right to D.Lovett pushed ob at DET 38 for 9 yards (J.Marshall).",
      "type": "Pass Reception",
      "down": 3,
      "distance": 12,
      "yard_line": 29,
      "period": 2,
      "clock": "1:18",
      "team": "",
      "scoring_play": false
    },
    {
      "id": "4017762642142",
      "text": "(Shotgun) K.Allen pass short middle to I.TeSlaa to DET 44 for 6 yards (J.Marshall) [G.Murphy].",
      "type": "Pass Reception",
      "down": 4,
      "distance": 3,
      "yard_line": 38,
      "period": 2,
      "clock": "1:14",
      "team": "",
      "scoring_play": false
    },
    {
      "id": "4017762642155",
      "text": "Timeout #1 by DET at 01:08.",
      "type": "Timeout",
      "down": 1,
      "distance": 10,
      "yard_line": 44,
      "period": 2,
      "clock": "1:08",
      "team": "",
      "scoring_play": false
    },
    {
      "id": "4017762642167",
      "text": "(Shotgun) K.Allen pass deep middle to J.Meeks to MIA 29 for 27 yards (J.Marshall).",
      "type": "Pass Reception",
      "down": 1,
      "distance": 10,
      "yard_line": 44,
      "period": 2,
      "clock": "1:08",
      "team": "",
      "scoring_play": false
    },
    {
      "id": "4017762642183",
      "text": "Timeout #2 by DET at 01:00.",
      "type": "Timeout",
      "down": 1,
      "distance": 10,
      "yard_line": 73,
      "period": 2,
      "clock": "1:00",
      "team": "",
      "scoring_play": false
    },
    {
      "id": "4017762642199",
      "text": "(Shotgun) S.Vaki up the middle to MIA 22 for 7 yards (C.Armstrong).",
      "type": "Rush",
      "down": 1,
      "distance": 10,
      "yard_line": 71,
      "period": 2,
      "clock": "1:00",
      "team": "",
      "scoring_play": false
    },
    {
      "id": "4017762642228",
      "text": "(No Huddle, Shotgun) K.Allen pass short right to S.Vaki to MIA 18 for 4 yards (D.Jackson; J.Marshall).",
      "type": "Pass Reception",
      "down": 2,
      "distance": 3,
      "yard_line": 78,
      "period": 2,
      "clock": "0:39",
      "team": "",
      "scoring_play": false
    },
    {
      "id": "4017762642241",
      "text": "Timeout #3 by DET at 00:37.",
      "type": "Timeout",
      "down": 1,
      "distance": 10,
      "yard_line": 82,
      "period": 2,
      "clock": "0:37",
      "team": "",
      "scoring_play": false
    },
    {
      "id": "4017762642253",
      "text": "(Shotgun) K.Allen pass deep left to I.TeSlaa for 18 yards, TOUCHDOWN. J.Bates extra point is GOOD, Center-H.Hatten, Holder-J.Fox.",
      "type": "Passing Touchdown",
      "down": 1,
      "distance": 10,
      "yard_line": 82,
      "period": 2,
      "clock": "0:30",
      "team": "",
      "scoring_play": true
    },
    {
      "id": "4017762642301",
      "text": "J.Bates kicks 60 yards from DET 35 to MIA 5. A.Henning pushed ob at MIA 36 for 31 yards (N.Whiteside).",
      "type": "Kickoff",
      "down": 0,
      "distance": 0,
      "yard_line": 35,
      "period": 2,
      "clock": "0:30",
      "team": "",
      "scoring_play": false
    },
    {
      "id": "4017762642329",
      "text": "(Shotgun) Z.Wilson pass short right to T.Washington to MIA 45 for 9 yards (N.Whiteside).",
      "type": "Pass Reception",
      "down": 1,
      "distance": 10,
      "yard_line": 64,
      "period": 2,
      "clock": "0:25",
      "team": "",
      "scoring_play": false
    },
    {
      "id": "4017762642359",
      "text": "(No Huddle, Shotgun) Z.Wilson pass short right to T.Conner to DET 44 for 11 yards (E.Turner).",
      "type": "Pass Reception",
      "down": 2,
      "distance": 1,
      "yard_line": 55,
      "period": 2,
      "clock": "0:06",
      "team": "",
      "scoring_play": false
    },
    {
      "id": "4017762642388",
      "text": "END QUARTER 2",
      "type": "End of Half",
      "down": 0,
      "distance": 0,
      "yard_line": 35,
      "period": 2,
      "clock": "0:00",
      "team": "",
      "scoring_play": false
    },
    {
      "id": "4017762642408",
      "text": "J.Bates kicks 62 yards from DET 35 to MIA 3, out of bounds.PENALTY on DET-J.Bates, Kickoff Out of Bounds, placed at MIA 40.",
      "type": "Kickoff",
      "down": 0,
      "distance": 0,
      "yard_line": 35,
      "period": 3,
      "clock": "15:00",
      "team": "",
      "scoring_play": false
    },
    {
      "id": "4017762642435",
      "text": "O.Gordon left tackle to MIA 44 for 4 yards (A.Pittman).",
      "type": "Rush",
      "down": 1,
      "distance": 10,
      "yard_line": 60,
      "period": 3,
      "clock": "15:00",
      "team": "",
      "scoring_play": false
    },
    {
      "id": "4017762642457",
      "text": "Q.Ewers pass incomplete short middle to T.Wease (N.Whiteside).",
      "type": "Pass Incompletion",
      "down": 2,
      "distance": 6,
      "yard_line": 56,
      "period": 3,
      "clock": "14:28",
      "team": "",
      "scoring_play": false
    },
    {
      "id": "4017762642480",
      "text": "(Shotgun) Q.Ewers pass incomplete short right to A.Henning.",
      "type": "Pass Incompletion",
      "down": 3,
      "distance": 6,
      "yard_line": 56,
      "period": 3,
      "clock": "14:23",
      "team": "",
      "scoring_play": false
    },
    {
      "id": "4017762642503",
      "text": "R.Stonehouse punts 42 yards to DET 14, Center-J.Cardona, fair catch by T.Kennedy.",
      "type": "Punt",
      "down": 4,
      "distance": 6,
      "yard_line": 56,
      "period": 3,
      "clock": "14:19",
      "team": "",
      "scoring_play": false
    },
    {
      "id": "4017762642534",
      "text": "J.Saylors left tackle to DET 13 for -1 yards (J.Marshall).",
      "type": "Rush",
      "down": 1,
      "distance": 10,
      "yard_line": 14,
      "period": 3,
      "clock": "14:12",
      "team": "",
      "scoring_play": false
    },
    {
      "id": "4017762642556",
      "text": "(Shotgun) H.Hooker sacked at DET 6 for -7 yards (Jo.Phillips).",
      "type": "Sack",
      "down": 2,
      "distance": 11,
      "yard_line": 13,
      "period": 3,
      "clock": "13:45",
      "team": "",
      "scoring_play": false
    },
    {
      "id": "4017762642576",
      "text": "J.Saylors up the middle to DET 7 for 1 yard (G.Murphy).",
      "type": "Rush",
      "down": 3,
      "distance": 18,
      "yard_line": 6,
      "period": 3,
      "clock": "13:10",
      "team": "",
      "scoring_play": false
    },
    {
      "id": "4017762642598",
      "text": "J.Fox punts 55 yards to MIA 38, Center-H.Hatten. A.Henning pushed ob at DET 36 for 26 yards (A.Pittman).",
      "type": "Punt",
      "down": 4,
      "distance": 17,
      "yard_line": 7,
      "period": 3,
      "clock": "12:35",
      "team": "",
      "scoring_play": false
    },
    {
      "id": "4017762642614",
      "text": "Official Timeout at 12:22.",
      "type": "Official Timeout",
      "down": 1,
      "distance": 10,
      "yard_line": 36,
      "period": 3,
      "clock": "12:22",
      "team": "",
      "scoring_play": false
    },
    {
      "id": "4017762642629",
      "text": "O.Gordon up the middle to DET 17 for 19 yards (L.Strickland; E.Turner).",
      "type": "Rush",
      "down": 1,
      "distance": 10,
      "yard_line": 36,
      "period": 3,
      "clock": "12:22",
      "team": "",
      "scoring_play": false
    },
    {
      "id": "4017762642658",
      "text": "Q.Ewers pass short right to T.Wease to DET 14 for 3 yards (D.Miller).",
      "type": "Pass Reception",
      "down": 1,
      "distance": 10,
      "yard_line": 17,
      "period": 3,
      "clock": "11:50",
      "team": "",
      "scoring_play": false
    },
    {
      "id": "4017762642683",
      "text": "O.Gordon left tackle to DET 15 for -1 yards (E.Turner, N.Lynn). DET-A.Hassanein was injured during the play.",
      "type": "Rush",
      "down": 2,
      "distance": 7,
      "yard_line": 14,
      "period": 3,
      "clock": "11:10",
      "team": "",
      "scoring_play": false
    },
    {
      "id": "4017762642696",
      "text": "Official Timeout at 10:56.",
      "type": "Official Timeout",
      "down": 3,
      "distance": 8,
      "yard_line": 15,
      "period": 3,
      "clock": "10:56",
      "team": "",
      "scoring_play": false
    },
    {
      "id": "4017762642708",
      "text": "(Shotgun) Q.Ewers pass short middle to T.Wease for 15 yards, TOUCHDOWN. J.Sanders extra point is GOOD, Center-J.Cardona, Holder-R.Stonehouse.",
      "type": "Passing Touchdown",
      "down": 3,
      "distance": 8,
      "yard_line": 15,
      "period": 3,
      "clock": "10:36",
      "team": "",
      "scoring_play": true
    },
    {
      "id": "4017762642756",
      "text": "J.Sanders kicks 64 yards from MIA 35 to DET 1. D.Jackson to DET 30 for 29 yards (D.Jackson).",
      "type": "Kickoff",
      "down": 0,
      "distance": 0,
      "yard_line": 65,
      "period": 3,
      "clock": "10:36",
      "team": "",
      "scoring_play": false
    },
    {
      "id": "4017762642784",
      "text": "H.Hooker sacked at DET 30 for 0 yards (sack split by Jo.Phillips and C.Goode).",
      "type": "Sack",
      "down": 1,
      "distance": 10,
      "yard_line": 30,
      "period": 3,
      "clock": "10:31",
      "team": "",
      "scoring_play": false
    },
    {
      "id": "4017762642804",
      "text": "(Shotgun) J.Saylors right end to DET 29 for -1 yards (E.Asante).",
      "type": "Rush",
      "down": 2,
      "distance": 10,
      "yard_line": 30,
      "period": 3,
      "clock": "9:55",
      "team": "",
      "scoring_play": false
    },
    {
      "id": "4017762642826",
      "text": "(Shotgun) H.Hooker pass incomplete short middle to J.Saylors.",
      "type": "Pass Incompletion",
      "down": 3,
      "distance": 11,
      "yard_line": 29,
      "period": 3,
      "clock": "9:20",
      "team": "",
      "scoring_play": false
    },
    {
      "id": "4017762642849",
      "text": "J.Fox punts 39 yards to MIA 32, Center-H.Hatten. A.Henning MUFFS catch, RECOVERED by DET-D.Lovett at MIA 27.",
      "type": "Muffed Punt Recovery (Opponent)",
      "down": 4,
      "distance": 11,
      "yard_line": 29,
      "period": 3,
      "clock": "9:16",
      "team": "",
      "scoring_play": false
    },
    {
      "id": "4017762642882",
      "text": "(Shotgun) J.Saylors up the middle to MIA 26 for 1 yard (Z.Biggers; D.Jackson).",
      "type": "Rush",
      "down": 1,
      "distance": 10,
      "yard_line": 73,
      "period": 3,
      "clock": "9:08",
      "team": "",
      "scoring_play": false
    },
    {
      "id": "4017762642905",
      "text": "(Shotgun) J.Saylors up the middle to MIA 19 for 7 yards (J.Saunders; Jo.Phillips).",
      "type": "Rush",
      "down": 2,
      "distance": 9,
      "yard_line": 74,
      "period": 3,
      "clock": "8:37",
      "team": "",
      "scoring_play": false
    },
    {
      "id": "4017762642927",
      "text": "J.Saylors left tackle to MIA 18 for 1 yard (D.Jackson; C.Tindall).",
      "type": "Rush",
      "down": 3,
      "distance": 2,
      "yard_line": 81,
      "period": 3,
      "clock": "8:03",
      "team": "",
      "scoring_play": false
    },
    {
      "id": "4017762642949",
      "text": "J.Saylors left tackle to MIA 14 for 4 yards (I.Johnson).",
      "type": "Rush",
      "down": 4,
      "distance": 1,
      "yard_line": 82,
      "period": 3,
      "clock": "7:36",
      "team": "",
      "scoring_play": false
    },
    {
      "id": "4017762642971",
      "text": "J.Saylors left tackle to MIA 13 for 1 yard (D.McLendon).",
      "type": "Rush",
      "down": 1,
      "distance": 10,
      "yard_line": 86,
      "period": 3,
      "clock": "6:59",
      "team": "",
      "scoring_play": false
    },
    {
      "id": "4017762642993",
      "text": "D.Jackson left tackle to MIA 10 for 3 yards (D.McLendon).",
      "type": "Rush",
      "down": 2,
      "distance": 9,
      "yard_line": 87,
      "period": 3,
      "clock": "6:24",
      "team": "",
      "scoring_play": false
    },
    {
      "id": "4017762643015",
      "text": "(Shotgun) H.Hooker scrambles left tackle for 10 yards, TOUCHDOWN NULLIFIED by Penalty.PENALTY on DET-G.Manu, Offensive Holding, 10 yards, enforced at MIA 10 - No Play.",
      "type": "Penalty",
      "down": 3,
      "distance": 6,
      "yard_line": 90,
      "period": 3,
      "clock": "5:47",
      "team": "",
      "scoring_play": false
    },
    {
      "id": "4017762643049",
      "text": "(Shotgun) H.Hooker pass short middle to J.Saylors to MIA 15 for 5 yards (C.Tindall) [G.Murphy].",
      "type": "Pass Reception",
      "down": 3,
      "distance": 16,
      "yard_line": 80,
      "period": 3,
      "clock": "5:39",
      "team": "",
      "scoring_play": false
    },
    {
      "id": "4017762643074",
      "text": "J.Bates 33 yard field goal is GOOD, Center-H.Hatten, Holder-J.Fox.",
      "type": "Field Goal Good",
      "down": 4,
      "distance": 11,
      "yard_line": 85,
      "period": 3,
      "clock": "4:53",
      "team": "",
      "scoring_play": true
    },
    {
      "id": "4017762643084",
      "text": "Official Timeout at 04:53.",
      "type": "Official Timeout",
      "down": 1,
      "distance": 10,
      "yard_line": 35,
      "period": 3,
      "clock": "4:53",
      "team": "",
      "scoring_play": false
    },
    {
      "id": "4017762643094",
      "text": "J.Bates kicks 63 yards from DET 35 to MIA 2. A.Henning to MIA 35 for 33 yards (A.Pittman).",
      "type": "Kickoff",
      "down": 0,
      "distance": 0,
      "yard_line": 35,
      "period": 3,
      "clock": "4:53",
      "team": "",
      "scoring_play": false
    },
    {
      "id": "4017762643141",
      "text": "(Shotgun) O.Gordon up the middle to MIA 37 for 2 yards (L.Strickland).",
      "type": "Rush",
      "down": 1,
      "distance": 10,
      "yard_line": 65,
      "period": 3,
      "clock": "4:47",
      "team": "",
      "scoring_play": false
    },
    {
      "id": "4017762643163",
      "text": "Q.Ewers pass incomplete short left to T.Black (E.Hallett).",
      "type": "Pass Incompletion",
      "down": 2,
      "distance": 8,
      "yard_line": 63,
      "period": 3,
      "clock": "4:08",
      "team": "",
      "scoring_play": false
    },
    {
      "id": "4017762643175",
      "text": "Timeout #1 by MIA at 04:04.",
      "type": "Timeout",
      "down": 3,
      "distance": 8,
      "yard_line": 63,
      "period": 3,
      "clock": "4:04",
      "team": "",
      "scoring_play": false
    },
    {
      "id": "4017762643186",
      "text": "(Shotgun) Q.Ewers pass short left to O.Gordon to MIA 32 for -5 yards (N.Lynn).",
      "type": "Pass Reception",
      "down": 3,
      "distance": 8,
      "yard_line": 63,
      "period": 3,
      "clock": "4:04",
      "team": "",
      "scoring_play": false
    },
    {
      "id": "4017762643218",
      "text": "J.Bailey punts 59 yards to DET 9, Center-J.Cardona, downed by MIA-D.Jackson.",
      "type": "Punt",
      "down": 4,
      "distance": 13,
      "yard_line": 68,
      "period": 3,
      "clock": "3:23",
      "team": "",
      "scoring_play": false
    },
    {
      "id": "4017762643238",
      "text": "D.Jackson left tackle to DET 16 for 7 yards (E.Asante; M.Butler).",
      "type": "Rush",
      "down": 1,
      "distance": 10,
      "yard_line": 9,
      "period": 3,
      "clock": "3:11",
      "team": "",
      "scoring_play": false
    },
    {
      "id": "4017762643260",
      "text": "D.Jackson right tackle to DET 18 for 2 yards (D.McLendon; B.Stille).",
      "type": "Rush",
      "down": 2,
      "distance": 3,
      "yard_line": 16,
      "period": 3,
      "clock": "2:41",
      "team": "",
      "scoring_play": false
    },
    {
      "id": "4017762643282",
      "text": "D.Jackson up the middle to DET 21 for 3 yards (E.Asante; D.McLendon).PENALTY on DET-J.Meeks, Illegal Shift, 5 yards, enforced at DET 18 - No Play.",
      "type": "Penalty",
      "down": 3,
      "distance": 1,
      "yard_line": 18,
      "period": 3,
      "clock": "1:58",
      "team": "",
      "scoring_play": false
    },
    {
      "id": "4017762643315",
      "text": "(Shotgun) H.Hooker pass short right to Z.Horton to DET 19 for 6 yards (C.Tindall).PENALTY on DET-Z.Johnson, Offensive Holding, 6 yards, enforced at DET 13 - No Play.",
      "type": "Penalty",
      "down": 3,
      "distance": 6,
      "yard_line": 13,
      "period": 3,
      "clock": "1:32",
      "team": "",
      "scoring_play": false
    },
    {
      "id": "4017762643351",
      "text": "(Shotgun) D.Jackson up the middle to DET 15 for 8 yards (C.Tindall; J.Colbert).",
      "type": "Rush",
      "down": 3,
      "distance": 12,
      "yard_line": 7,
      "period": 3,
      "clock": "1:09",
      "team": "",
      "scoring_play": false
    },
    {
      "id": "4017762643373",
      "text": "J.Fox punts 60 yards to MIA 25, Center-H.Hatten. A.Henning ran ob at MIA 40 for 15 yards (A.Pittman).",
      "type": "Punt",
      "down": 4,
      "distance": 4,
      "yard_line": 15,
      "period": 3,
      "clock": "0:32",
      "team": "",
      "scoring_play": false
    },
    {
      "id": "4017762643404",
      "text": "PENALTY on DET-B.Martin, Neutral Zone Infraction, 5 yards, enforced at MIA 40 - No Play.",
      "type": "Penalty",
      "down": 1,
      "distance": 10,
      "yard_line": 60,
      "period": 3,
      "clock": "0:19",
      "team": "",
      "scoring_play": false
    },
    {
      "id": "4017762643428",
      "text": "Q.Ewers pass short middle to T.Wease to DET 32 for 23 yards (E.Turner).",
      "type": "Pass Reception",
      "down": 1,
      "distance": 5,
      "yard_line": 55,
      "period": 3,
      "clock": "0:19",
      "team": "",
      "scoring_play": false
    },
    {
      "id": "4017762643453",
      "text": "END QUARTER 3",
      "type": "End Period",
      "down": 1,
      "distance": 10,
      "yard_line": 32,
      "period": 3,
      "clock": "0:00",
      "team": "",
      "scoring_play": false
    },
    {
      "id": "4017762643473",
      "text": "O.Gordon up the middle to DET 26 for 6 yards (D.Gilbert; E.Turner).",
      "type": "Rush",
      "down": 1,
      "distance": 10,
      "yard_line": 32,
      "period": 4,
      "clock": "15:00",
      "team": "",
      "scoring_play": false
    },
    {
      "id": "4017762643495",
      "text": "O.Gordon up the middle to DET 23 for 3 yards (M.Adams; E.Turner).",
      "type": "Rush",
      "down": 2,
      "distance": 4,
      "yard_line": 26,
      "period": 4,
      "clock": "14:23",
      "team": "",
      "scoring_play": false
    },
    {
      "id": "4017762643517",
      "text": "(Shotgun) O.Gordon left tackle to DET 8 for 15 yards (E.Turner, E.Hallett).",
      "type": "Rush",
      "down": 3,
      "distance": 1,
      "yard_line": 23,
      "period": 4,
      "clock": "13:38",
      "team": "",
      "scoring_play": false
    },
    {
      "id": "4017762643539",
      "text": "(Shotgun) O.Gordon up the middle to DET 8 for no gain (D.Gilbert; E.Turner).",
      "type": "Rush",
      "down": 1,
      "distance": 8,
      "yard_line": 8,
      "period": 4,
      "clock": "13:00",
      "team": "",
      "scoring_play": false
    },
    {
      "id": "4017762643561",
      "text": "Q.Ewers pass short left to T.Wease for 8 yards, TOUCHDOWN. J.Sanders extra point is GOOD, Center-J.Cardona, Holder-J.Bailey.",
      "type": "Passing Touchdown",
      "down": 2,
      "distance": 8,
      "yard_line": 8,
      "period": 4,
      "clock": "12:16",
      "team": "",
      "scoring_play": true
    },
    {
      "id": "4017762643595",
      "text": "Official Timeout at 12:16.",
      "type": "Official Timeout",
      "down": 1,
      "distance": 10,
      "yard_line": 65,
      "period": 4,
      "clock": "12:16",
      "team": "",
      "scoring_play": false
    },
    {
      "id": "4017762643602",
      "text": "J.Sanders kicks 61 yards from MIA 35 to DET 4. J.Saylors to DET 28 for 24 yards (D.Jackson). MIA-D.Jackson was injured during the play.",
      "type": "Kickoff",
      "down": 0,
      "distance": 0,
      "yard_line": 65,
      "period": 4,
      "clock": "12:16",
      "team": "",
      "scoring_play": false
    },
    {
      "id": "4017762643632",
      "text": "H.Hooker pass short left to Z.Horton ran ob at DET 37 for 9 yards (G.Murphy).",
      "type": "Pass Reception",
      "down": 1,
      "distance": 10,
      "yard_line": 28,
      "period": 4,
      "clock": "12:11",
      "team": "",
      "scoring_play": false
    },
    {
      "id": "4017762643668",
      "text": "J.Saylors left tackle to DET 39 for 2 yards (C.Tindall; M.Dickerson).",
      "type": "Rush",
      "down": 2,
      "distance": 1,
      "yard_line": 37,
      "period": 4,
      "clock": "11:36",
      "team": "",
      "scoring_play": false
    },
    {
      "id": "4017762643690",
      "text": "H.Hooker pass incomplete deep middle to J.Keeney-James.",
      "type": "Pass Incompletion",
      "down": 1,
      "distance": 10,
      "yard_line": 39,
      "period": 4,
      "clock": "11:00",
      "team": "",
      "scoring_play": false
    },
    {
      "id": "4017762643713",
      "text": "(Shotgun) J.Saylors left end pushed ob at DET 48 for 9 yards (J.Saunders).",
      "type": "Rush",
      "down": 2,
      "distance": 10,
      "yard_line": 39,
      "period": 4,
      "clock": "10:55",
      "team": "",
      "scoring_play": false
    },
    {
      "id": "4017762643740",
      "text": "H.Hooker sacked at DET 48 for 0 yards (C.Smith).PENALTY on DET, Illegal Shift, 5 yards, enforced at DET 48 - No Play.",
      "type": "Penalty",
      "down": 3,
      "distance": 1,
      "yard_line": 48,
      "period": 4,
      "clock": "10:11",
      "team": "",
      "scoring_play": false
    },
    {
      "id": "4017762643780",
      "text": "(Shotgun) H.Hooker pass incomplete short left to Z.Horton [B.Stille].",
      "type": "Pass Incompletion",
      "down": 3,
      "distance": 6,
      "yard_line": 43,
      "period": 4,
      "clock": "9:56",
      "team": "",
      "scoring_play": false
    },
    {
      "id": "4017762643803",
      "text": "J.Fox punts 47 yards to MIA 10, Center-H.Hatten, out of bounds.PENALTY on MIA-E.Ezukanma, Unnecessary Roughness, 5 yards, enforced at MIA 10.",
      "type": "Punt",
      "down": 4,
      "distance": 6,
      "yard_line": 43,
      "period": 4,
      "clock": "9:51",
      "team": "",
      "scoring_play": false
    },
    {
      "id": "4017762643821",
      "text": "Official Timeout at 09:43.",
      "type": "Official Timeout",
      "down": 1,
      "distance": 10,
      "yard_line": 95,
      "period": 4,
      "clock": "9:43",
      "team": "",
      "scoring_play": false
    },
    {
      "id": "4017762643839",
      "text": "M.Boone up the middle to MIA 13 for 8 yards (E.Turner; D.Miller).",
      "type": "Rush",
      "down": 1,
      "distance": 10,
      "yard_line": 95,
      "period": 4,
      "clock": "9:43",
      "team": "",
      "scoring_play": false
    },
    {
      "id": "4017762643868",
      "text": "Q.Ewers pass incomplete short right to A.Armstrong (L.Barcoo).",
      "type": "Pass Incompletion",
      "down": 2,
      "distance": 2,
      "yard_line": 87,
      "period": 4,
      "clock": "9:02",
      "team": "",
      "scoring_play": false
    },
    {
      "id": "4017762643891",
      "text": "(Shotgun) PENALTY on MIA, Delay of Game, 5 yards, enforced at MIA 13 - No Play.",
      "type": "Penalty",
      "down": 3,
      "distance": 2,
      "yard_line": 87,
      "period": 4,
      "clock": "8:57",
      "team": "",
      "scoring_play": false
    },
    {
      "id": "4017762643915",
      "text": "(Shotgun) Q.Ewers pass short middle to A.Henning to MIA 20 for 12 yards (T.Russell).",
      "type": "Pass Reception",
      "down": 3,
      "distance": 7,
      "yard_line": 92,
      "period": 4,
      "clock": "8:57",
      "team": "",
      "scoring_play": false
    },
    {
      "id": "4017762643940",
      "text": "Q.Ewers pass deep middle to T.Wease to MIA 37 for 17 yards (L.Barcoo).",
      "type": "Pass Reception",
      "down": 1,
      "distance": 10,
      "yard_line": 80,
      "period": 4,
      "clock": "8:18",
      "team": "",
      "scoring_play": false
    },
    {
      "id": "4017762643965",
      "text": "(Shotgun) Q.Ewers pass short middle to C.Myarick to 50 for 13 yards (L.Strickland).",
      "type": "Pass Reception",
      "down": 1,
      "distance": 10,
      "yard_line": 63,
      "period": 4,
      "clock": "7:34",
      "team": "",
      "scoring_play": false
    },
    {
      "id": "4017762643990",
      "text": "Q.Ewers pass incomplete short right to A.Armstrong.PENALTY on MIA-H.Rucci, Offensive Holding, 10 yards, enforced at 50 - No Play.",
      "type": "Penalty",
      "down": 1,
      "distance": 10,
      "yard_line": 50,
      "period": 4,
      "clock": "6:57",
      "team": "",
      "scoring_play": false
    },
    {
      "id": "4017762644024",
      "text": "(Shotgun) A.Shampklin right tackle to DET 34 for 26 yards (E.Hallett; L.Barcoo).",
      "type": "Rush",
      "down": 1,
      "distance": 20,
      "yard_line": 60,
      "period": 4,
      "clock": "6:53",
      "team": "",
      "scoring_play": false
    },
    {
      "id": "4017762644046",
      "text": "(Shotgun) Q.Ewers pass incomplete deep left to A.Henning.PENALTY on MIA-A.Henning, Offensive Pass Interference, 10 yards, enforced at DET 34 - No Play.",
      "type": "Penalty",
      "down": 1,
      "distance": 10,
      "yard_line": 34,
      "period": 4,
      "clock": "6:08",
      "team": "",
      "scoring_play": false
    },
    {
      "id": "4017762644080",
      "text": "(Shotgun) Q.Ewers pass incomplete short left to T.Wease (D.Miller).",
      "type": "Pass Incompletion",
      "down": 1,
      "distance": 20,
      "yard_line": 44,
      "period": 4,
      "clock": "6:03",
      "team": "",
      "scoring_play": false
    },
    {
      "id": "4017762644114",
      "text": "(Shotgun) Q.Ewers pass short right to A.Armstrong to DET 32 for 12 yards (L.Barcoo).",
      "type": "Pass Reception",
      "down": 2,
      "distance": 20,
      "yard_line": 44,
      "period": 4,
      "clock": "6:00",
      "team": "",
      "scoring_play": false
    },
    {
      "id": "4017762644144",
      "text": "(Shotgun) Q.Ewers pass short left to T.Wease to DET 18 for 14 yards (D.Miller).",
      "type": "Pass Reception",
      "down": 3,
      "distance": 8,
      "yard_line": 32,
      "period": 4,
      "clock": "5:18",
      "team": "",
      "scoring_play": false
    },
    {
      "id": "4017762644169",
      "text": "(Shotgun) A.Shampklin left tackle to DET 12 for 6 yards (A.Pittman; N.Lynn).",
      "type": "Rush",
      "down": 1,
      "distance": 10,
      "yard_line": 18,
      "period": 4,
      "clock": "4:38",
      "team": "",
      "scoring_play": false
    },
    {
      "id": "4017762644191",
      "text": " (Shotgun) M.Boone up the middle to DET 5 for 7 yards (N.Whiteside).",
      "type": "Rush",
      "down": 2,
      "distance": 4,
      "yard_line": 12,
      "period": 4,
      "clock": "3:59",
      "team": "",
      "scoring_play": false
    },
    {
      "id": "4017762644213",
      "text": "(Shotgun) Q.Ewers pass short middle to A.Henning to DET 1 for 4 yards (N.Whiteside; L.Strickland).",
      "type": "Pass Reception",
      "down": 1,
      "distance": 5,
      "yard_line": 5,
      "period": 4,
      "clock": "3:20",
      "team": "",
      "scoring_play": false
    },
    {
      "id": "4017762644238",
      "text": "M.Boone right tackle to DET 3 for -2 yards (D.Gilbert, N.Lynn).",
      "type": "Rush",
      "down": 2,
      "distance": 1,
      "yard_line": 1,
      "period": 4,
      "clock": "2:39",
      "team": "",
      "scoring_play": false
    },
    {
      "id": "4017762644249",
      "text": "Two-Minute Warning",
      "type": "Two-minute warning",
      "down": 3,
      "distance": 4,
      "yard_line": 4,
      "period": 4,
      "clock": "2:00",
      "team": "",
      "scoring_play": false
    },
    {
      "id": "4017762644260",
      "text": "Q.Ewers pass incomplete short right to T.Wease (E.Hallett).",
      "type": "Pass Incompletion",
      "down": 3,
      "distance": 3,
      "yard_line": 3,
      "period": 4,
      "clock": "2:00",
      "team": "",
      "scoring_play": false
    },
    {
      "id": "4017762644290",
      "text": "J.Sanders 22 yard field goal is GOOD, Center-J.Cardona, Holder-R.Stonehouse.",
      "type": "Field Goal Good",
      "down": 4,
      "distance": 3,
      "yard_line": 3,
      "period": 4,
      "clock": "1:50",
      "team": "",
      "scoring_play": true
    },
    {
      "id": "4017762644300",
      "text": "Official Timeout at 01:50.",
      "type": "Official Timeout",
      "down": 1,
      "distance": 10,
      "yard_line": 65,
      "period": 4,
      "clock": "1:50",
      "team": "",
      "scoring_play": false
    },
    {
      "id": "4017762644310",
      "text": "J.Sanders kicks 63 yards from MIA 35 to DET 2. J.Saylors to DET 39 for 37 yards (J.Sanders; I.Johnson).",
      "type": "Kickoff",
      "down": 0,
      "distance": 0,
      "yard_line": 65,
      "period": 4,
      "clock": "1:50",
      "team": "",
      "scoring_play": false
    },
    {
      "id": "4017762644340",
      "text": "(Shotgun) H.Hooker pass incomplete short right to J.Meeks (Z.Biggers).",
      "type": "Pass Incompletion",
      "down": 1,
      "distance": 10,
      "yard_line": 39,
      "period": 4,
      "clock": "1:42",
      "team": "",
      "scoring_play": false
    },
    {
      "id": "4017762644363",
      "text": "(Shotgun) H.Hooker pass short right to J.Meeks to 50 for 11 yards (I.Johnson; C.Smith).",
      "type": "Pass Reception",
      "down": 2,
      "distance": 10,
      "yard_line": 39,
      "period": 4,
      "clock": "1:39",
      "team": "",
      "scoring_play": false
    },
    {
      "id": "4017762644388",
      "text": "(No Huddle, Shotgun) H.Hooker pass incomplete short middle to J.Saylors (E.Asante).",
      "type": "Pass Incompletion",
      "down": 1,
      "distance": 10,
      "yard_line": 50,
      "period": 4,
      "clock": "1:21",
      "team": "",
      "scoring_play": false
    },
    {
      "id": "4017762644423",
      "text": "(Shotgun) H.Hooker pass short middle to R.Bell to MIA 39 for 11 yards (E.Robinson; C.Tindall).",
      "type": "Pass Reception",
      "down": 2,
      "distance": 10,
      "yard_line": 50,
      "period": 4,
      "clock": "1:13",
      "team": "",
      "scoring_play": false
    },
    {
      "id": "4017762644448",
      "text": "(No Huddle, Shotgun) H.Hooker pass short right to J.Meeks to MIA 30 for 9 yards (E.Asante).",
      "type": "Pass Reception",
      "down": 1,
      "distance": 10,
      "yard_line": 61,
      "period": 4,
      "clock": "0:54",
      "team": "",
      "scoring_play": false
    },
    {
      "id": "4017762644473",
      "text": "Timeout #1 by DET at 00:48.",
      "type": "Timeout",
      "down": 2,
      "distance": 1,
      "yard_line": 70,
      "period": 4,
      "clock": "0:48",
      "team": "",
      "scoring_play": false
    },
    {
      "id": "4017762644480",
      "text": "(Shotgun) H.Hooker scrambles right tackle to MIA 29 for 1 yard (I.Johnson).",
      "type": "Rush",
      "down": 2,
      "distance": 1,
      "yard_line": 70,
      "period": 4,
      "clock": "0:48",
      "team": "",
      "scoring_play": false
    },
    {
      "id": "4017762644491",
      "text": "Timeout #2 by DET at 00:41.",
      "type": "Timeout",
      "down": 1,
      "distance": 10,
      "yard_line": 71,
      "period": 4,
      "clock": "0:41",
      "team": "",
      "scoring_play": false
    },
    {
      "id": "4017762644502",
      "text": "(Shotgun) H.Hooker pass short left to J.Meeks to MIA 13 for 16 yards (E.Asante; E.Robinson).",
      "type": "Pass Reception",
      "down": 1,
      "distance": 10,
      "yard_line": 71,
      "period": 4,
      "clock": "0:41",
      "team": "",
      "scoring_play": false
    },
    {
      "id": "4017762644534",
      "text": "(No Huddle) H.Hooker spiked the ball to stop the clock.",
      "type": "Pass Incompletion",
      "down": 1,
      "distance": 10,
      "yard_line": 87,
      "period": 4,
      "clock": "0:28",
      "team": "",
      "scoring_play": false
    },
    {
      "id": "4017762644566",
      "text": "(Shotgun) H.Hooker pass short right intended for Z.Horton INTERCEPTED by E.Robinson at MIA 20. E.Robinson to MIA 22 for 2 yards (J.Saylors).",
      "type": "Pass Interception Return",
      "down": 2,
      "distance": 10,
      "yard_line": 87,
      "period": 4,
      "clock": "0:27",
      "team": "",
      "scoring_play": false
    },
    {
      "id": "4017762644593",
      "text": "Q.Ewers kneels to MIA 21 for -1 yards.",
      "type": "Rush",
      "down": 1,
      "distance": 10,
      "yard_line": 78,
      "period": 4,
      "clock": "0:22",
      "team": "",
      "scoring_play": false
    },
    {
      "id": "4017762644615",
      "text": "END GAME",
      "type": "End of Game",
      "down": 0,
      "distance": 0,
      "yard_line": 79,
      "period": 4,
      "clock": "0:00",
      "team": "",
      "scoring_play": false
    }
  ],
  "scoring_plays": [],
  "touchdowns": [
    {
      "play_id": "401776264949",
      "text": "(Shotgun) Z.Wilson pass short left to D.Eskridge for 11 yards, TOUCHDOWN. J.Sanders extra point is GOOD, Center-J.Cardona, Holder-J.Bailey.",
      "team": "",
      "period": 1,
      "players_involved": []
    },
    {
      "play_id": "4017762641616",
      "text": "(Shotgun) K.Allen pass short left to J.Meeks for 11 yards, TOUCHDOWN. J.Bates extra point is GOOD, Center-H.Hatten, Holder-J.Fox.",
      "team": "",
      "period": 2,
      "players_involved": []
    },
    {
      "play_id": "4017762642253",
      "text": "(Shotgun) K.Allen pass deep left to I.TeSlaa for 18 yards, TOUCHDOWN. J.Bates extra point is GOOD, Center-H.Hatten, Holder-J.Fox.",
      "team": "",
      "period": 2,
      "players_involved": []
    },
    {
      "play_id": "4017762642708",
      "text": "(Shotgun) Q.Ewers pass short middle to T.Wease for 15 yards, TOUCHDOWN. J.Sanders extra point is GOOD, Center-J.Cardona, Holder-R.Stonehouse.",
      "team": "",
      "period": 3,
      "players_involved": []
    },
    {
      "play_id": "4017762643561",
      "text": "Q.Ewers pass short left to T.Wease for 8 yards, TOUCHDOWN. J.Sanders extra point is GOOD, Center-J.Cardona, Holder-J.Bailey.",
      "team": "",
      "period": 4,
      "players_involved": []
    }
  ],
  "interceptions": [
    {
      "play_id": "4017762644566",
      "text": "(Shotgun) H.Hooker pass short right intended for Z.Horton INTERCEPTED by E.Robinson at MIA 20. E.Robinson to MIA 22 for 2 yards (J.Saylors).",
      "team": "",
      "period": 4,
      "players_involved": []
    }
  ],
  "fumbles": []
}